dispel4py/__init__.py
dispel4py/__main__.py
dispel4py/base.py
dispel4py/core.py
dispel4py/provenance.py
dispel4py/utils.py
dispel4py/visualisation.py
dispel4py/workflow_graph.py
dispel4py/examples/__init__.py
dispel4py/examples/graph_testing/__init__.py
dispel4py/examples/graph_testing/delayed_pipeline.py
dispel4py/examples/graph_testing/group_by.py
dispel4py/examples/graph_testing/group_by_stateful.py
dispel4py/examples/graph_testing/grouping_alltoone.py
dispel4py/examples/graph_testing/grouping_alltoone_stateful.py
dispel4py/examples/graph_testing/grouping_onetoall.py
dispel4py/examples/graph_testing/grouping_onetoall_stateful.py
dispel4py/examples/graph_testing/grouping_split_merge.py
dispel4py/examples/graph_testing/large_teecopy.py
dispel4py/examples/graph_testing/parallel_pipeline.py
dispel4py/examples/graph_testing/partition_parallel_pipeline.py
dispel4py/examples/graph_testing/pipeline_composite.py
dispel4py/examples/graph_testing/pipeline_test.py
dispel4py/examples/graph_testing/producer_tee.py
dispel4py/examples/graph_testing/split_merge.py
dispel4py/examples/graph_testing/teecopy.py
dispel4py/examples/graph_testing/testing_PEs.py
dispel4py/examples/graph_testing/unconnected_pipeline.py
dispel4py/examples/graph_testing/word_count.py
dispel4py/examples/graph_testing/word_count_filter.py
dispel4py/new/__init__.py
dispel4py/new/aggregate.py
dispel4py/new/dyn_redis_config.py
dispel4py/new/dynamic_redis.py
dispel4py/new/logger.py
dispel4py/new/mappings.py
dispel4py/new/monitoring.py
dispel4py/new/mpi_process.py
dispel4py/new/multi_process.py
dispel4py/new/new_dynamic.py
dispel4py/new/new_dynamic_auto.py
dispel4py/new/new_dynamic_redis.py
dispel4py/new/new_dynamic_redis_auto.py
dispel4py/new/new_hybrid_redis.py
dispel4py/new/processor.py
dispel4py/new/simple_process.py
dispel4py/new/spark_process.py
dispel4py/new/zmq_multi.py
stream_d4py-2.9.1.dist-info/LICENSE
stream_d4py-2.9.1.dist-info/METADATA
stream_d4py-2.9.1.dist-info/WHEEL
stream_d4py-2.9.1.dist-info/entry_points.txt
stream_d4py-2.9.1.dist-info/top_level.txt
stream_d4py-2.9.1.dist-info/RECORD
