Metadata-Version: 2.1
Name: stream-d4py
Version: 2.9.1
Summary: dispel4py is a free and open-source Python library for describing abstract stream-based workflows for distributed data-intensive applications.
Home-page: https://github.com/StreamingFlow/d4py/
Author: Rosa Filgueira and Amy Krauser
Author-email: rosa.filgueira.vicente@gmail.com
License: Apache 2
Keywords: updated dispel4py dispel workflows processing elements data intensive
Platform: UNKNOWN
Classifier: Development Status :: 3 - Alpha
Classifier: Topic :: Utilities
Classifier: Programming Language :: Python
Classifier: Programming Language :: Python :: 3
Classifier: Programming Language :: Python :: 3.10
Classifier: Operating System :: OS Independent
Requires-Python: >=3.10
Requires-Dist: flake8
Requires-Dist: networkx
Requires-Dist: pyzmq
Requires-Dist: redis
Requires-Dist: regex
Requires-Dist: tqdm
Requires-Dist: urllib3
Requires-Dist: setuptools
Requires-Dist: coloredlogs
Requires-Dist: ujson
Requires-Dist: jwt
Requires-Dist: numpy
